panther_detections/__init__.py
panther_detections/panther.py
panther_detections/panther_audit.py
panther_detections/panther_base_helpers.py
panther_detections/panther_box_helpers.py
panther_detections/panther_event_type_helpers.py
panther_detections/panther_iocs.py
panther_detections/panther_oss_helpers.py
panther_detections/aws_account_policies/__init__.py
panther_detections/aws_account_policies/aws_password_policy_complexity_guidelines.py
panther_detections/aws_account_policies/aws_password_policy_password_age_limit.py
panther_detections/aws_account_policies/aws_password_policy_password_reuse.py
panther_detections/aws_account_policies/aws_resource_minimum_tags.py
panther_detections/aws_account_policies/aws_resource_required_tags.py
panther_detections/aws_acm_policies/__init__.py
panther_detections/aws_acm_policies/aws_acm_certificate_expiration.py
panther_detections/aws_acm_policies/aws_acm_certificate_has_secure_algorithms.py
panther_detections/aws_acm_policies/aws_acm_certificate_valid.py
panther_detections/aws_cloudformation_policies/__init__.py
panther_detections/aws_cloudformation_policies/aws_cloudformation_stack_drifted.py
panther_detections/aws_cloudformation_policies/aws_cloudformation_stack_uses_iam_role.py
panther_detections/aws_cloudformation_policies/aws_cloudformation_termination_protection.py
panther_detections/aws_cloudtrail_policies/__init__.py
panther_detections/aws_cloudtrail_policies/aws_cloudtrail_cloudwatch_logs.py
panther_detections/aws_cloudtrail_policies/aws_cloudtrail_enabled.py
panther_detections/aws_cloudtrail_policies/aws_cloudtrail_log_encryption.py
panther_detections/aws_cloudtrail_policies/aws_cloudtrail_log_validation.py
panther_detections/aws_cloudtrail_policies/aws_cloudtrail_s3_bucket_access_logging.py
panther_detections/aws_cloudtrail_policies/aws_cloudtrail_s3_bucket_public.py
panther_detections/aws_cloudtrail_rules/__init__.py
panther_detections/aws_cloudtrail_rules/aws_ami_modified_for_public_access.py
panther_detections-0.0.3.dist-info/METADATA
panther_detections-0.0.3.dist-info/WHEEL
panther_detections-0.0.3.dist-info/top_level.txt
panther_detections-0.0.3.dist-info/RECORD
