Metadata-Version: 2.1
Name: panther-detections
Version: 0.0.3
Summary: panther_analysis detections exposed in a convienent python module
Home-page: UNKNOWN
License: UNKNOWN
Platform: UNKNOWN
Requires-Dist: policyuniverse
Requires-Dist: requests
Requires-Dist: jsonpath-ng
